sskb/__init__.py
sskb/data_model.py
sskb/skb.py
sskb/data_access/__init__.py
sskb/data_access/esnli.py
sskb/data_access/nli4ct.py
sskb/data_access/proofwiki.py
sskb/data_access/worldtree.py
sskb-0.1.6.dist-info/METADATA
sskb-0.1.6.dist-info/WHEEL
sskb-0.1.6.dist-info/top_level.txt
sskb-0.1.6.dist-info/RECORD
