Metadata-Version: 2.4
Name: sskb
Version: 0.1.6
Summary: Knowledge Base loading and annotation facilities
Home-page: 
Author: Danilo S. Carvalho
Author-email: "Danilo S. Carvalho" <danilo.carvalho@manchester.ac.uk>
Project-URL: Homepage, https://github.com/neuro-symbolic-ai/SSKB
Project-URL: Issues, https://github.com/neuro-symbolic-ai/SSKB/issues
Keywords: knowledge bases,annotated,nlp
Classifier: Programming Language :: Python :: 3
Classifier: Operating System :: OS Independent
Requires-Python: >=3.9
Requires-Dist: saf-nlp
Requires-Dist: tqdm
Requires-Dist: spacy
Requires-Dist: xxhash
Dynamic: author
